MANIFEST.in
README
setup.py
autocomplete/__init__.py
autocomplete/widgets.py
autocomplete/static/jquery.autocomplete.css
autocomplete/static/admin/js/jquery.autocomplete.js
django_autocomplete_foreignkey.egg-info/PKG-INFO
django_autocomplete_foreignkey.egg-info/SOURCES.txt
django_autocomplete_foreignkey.egg-info/dependency_links.txt
django_autocomplete_foreignkey.egg-info/top_level.txt