Metadata-Version: 1.0
Name: django-autocomplete-foreignkey
Version: 0.0.1
Summary: AutoComplete for ForeignKey and ManyToManyField.
Home-page: https://github.com/redhog/django-autocomplete
Author: nikolovski.darko@gmail.com
Author-email: nikolovski.darko@gmail.com
License: GPL
Keywords: django autocomplete foreignkey
Platform: UNKNOWN
